terminal_graphics/__init__.py
terminal_graphics/__main__.py
terminal_graphics/iterm.py
terminal_graphics/kitty.py
terminal_graphics/sixel.py
terminal_graphics/terminal.py
terminal_graphics/utils.py
terminal_graphics/version.py
terminal_graphics-0.27.0.dist-info/LICENSE
terminal_graphics-0.27.0.dist-info/METADATA
terminal_graphics-0.27.0.dist-info/WHEEL
terminal_graphics-0.27.0.dist-info/entry_points.txt
terminal_graphics-0.27.0.dist-info/top_level.txt
terminal_graphics-0.27.0.dist-info/RECORD
