Metadata-Version: 2.1
Name: terminal-graphics
Version: 0.27.0
Summary: Images in the terminal.
Home-page: https://github.com/eerimoq/terminal_graphics
Author: Erik Moqvist
Author-email: erik.moqvist@gmail.com
License: MIT
Keywords: terminal,image
Requires-Python: >=3.6
License-File: LICENSE
Requires-Dist: Pillow
Requires-Dist: numpy
Requires-Dist: rich
